pippackagelist/__init__.py
pippackagelist/__main__.py
pippackagelist/entry.py
pippackagelist/error.py
pippackagelist/identify_package_list_file_type.py
pippackagelist/list_packages_from_files.py
pippackagelist/parse_requirements_list.py
pippackagelist/parse_requirements_txt.py
pippackagelist/parse_setup_py.py
pip_package_list-0.0.11.dist-info/LICENSE
pip_package_list-0.0.11.dist-info/METADATA
pip_package_list-0.0.11.dist-info/WHEEL
pip_package_list-0.0.11.dist-info/entry_points.txt
pip_package_list-0.0.11.dist-info/top_level.txt
pip_package_list-0.0.11.dist-info/RECORD
