Metadata-Version: 2.1
Name: pip-package-list
Version: 0.0.11
Summary: Generate a flat list of packages Pip would install.
Home-page: https://github.com/Photonios/pip-package-list
Author: Swen Kooij
Author-email: swenkooij@gmail.com
License: MIT License
Keywords: pip,package,resolver,list,requirements
Classifier: Intended Audience :: Developers
Classifier: License :: OSI Approved :: MIT License
Classifier: Operating System :: OS Independent
Classifier: Programming Language :: Python
Classifier: Programming Language :: Python :: 3.5
Requires-Python: >=3.7
License-File: LICENSE
Requires-Dist: setuptools
Provides-Extra: analysis
Requires-Dist: black (==19.10b0) ; extra == 'analysis'
Requires-Dist: flake8 (==3.7.7) ; extra == 'analysis'
Requires-Dist: autoflake (==1.3) ; extra == 'analysis'
Requires-Dist: autopep8 (==1.4.4) ; extra == 'analysis'
Requires-Dist: isort (==4.3.20) ; extra == 'analysis'
Requires-Dist: docformatter (==1.3.1) ; extra == 'analysis'
Provides-Extra: test
Requires-Dist: pytest (==5.2.2) ; extra == 'test'
Requires-Dist: pytest-cov (==2.8.1) ; extra == 'test'
